Metadata-Version: 2.1
Name: krules-k8s-functions
Version: 0.11.1
Summary: KRules k8s subjects storage implementation
Home-page: https://github.com/airspot-dev/krules-subjects-storage-k8s.git
Author: Alberto Degli Esposti
Author-email: alberto@arispot.tech
License: Apache Licence 2.0
Keywords: krules kubernetes k8s python python knative
Platform: UNKNOWN
Classifier: Development Status :: 3 - Alpha
Classifier: License :: OSI Approved :: Apache Software License
License-File: LICENSE
License-File: AUTHORS
